memodo.py
memodo-1.0.0.dist-info/LICENSE
memodo-1.0.0.dist-info/METADATA
memodo-1.0.0.dist-info/WHEEL
memodo-1.0.0.dist-info/top_level.txt
memodo-1.0.0.dist-info/RECORD
