Metadata-Version: 2.1
Name: memodo
Version: 1.0.0
Summary: Memodo: An linear attention solution
Author: Project VsingerXiaoice Group
Author-email: alan_sudo@yeah.net
License: The Unlicense
Requires: torch
License-File: LICENSE
